mongoengine_history/__init__.py
mongoengine_history/montoengine_history.py
mongoengine_history-1.1.dist-info/DESCRIPTION.rst
mongoengine_history-1.1.dist-info/METADATA
mongoengine_history-1.1.dist-info/RECORD
mongoengine_history-1.1.dist-info/WHEEL
mongoengine_history-1.1.dist-info/metadata.json
mongoengine_history-1.1.dist-info/top_level.txt
