Metadata-Version: 2.0
Name: mongoengine-history
Version: 1.1
Summary: Track the documents changes
Home-page: https://github.com/maxpowel/mongoengine-history
Author: Álvaro García Gómez
Author-email: maxpowel@gmail.com
License: UNKNOWN
Download-URL: https://github.com/maxpowel/mongoengine-history/archive/master.zip
Keywords: mongoengine,dictdiff,diff,history,log,dictdiffer
Platform: UNKNOWN
Classifier: Topic :: Adaptive Technologies
Classifier: Topic :: Software Development
Classifier: Topic :: System
Classifier: Topic :: Utilities
Requires-Dist: blinker
Requires-Dist: dictdiffer
Requires-Dist: mongoengine
